mydavorpkg/MyPkg.py
mydavorpkg/__init__.py
mydavorpkg-0.1.0.dist-info/WHEEL
mydavorpkg-0.1.0.dist-info/METADATA
mydavorpkg-0.1.0.dist-info/RECORD
